pynndb/__init__.py
pynndb/compression.py
pynndb/cursor.py
pynndb/database.py
pynndb/decorators.py
pynndb/doc.py
pynndb/exceptions.py
pynndb/filterresult.py
pynndb/index.py
pynndb/manager.py
pynndb/metadata.py
pynndb/objectid.py
pynndb/replication.py
pynndb/serialiser.py
pynndb/table.py
pynndb/types_.py
pynndb2-2.2.9.data/data/xaml/Pipfile
pynndb2-2.2.9.data/data/xaml/README-PYPI.md
pynndb2-2.2.9.data/data/xaml/coveragerc
pynndb2-2.2.9.dist-info/LICENSE
pynndb2-2.2.9.dist-info/METADATA
pynndb2-2.2.9.dist-info/WHEEL
pynndb2-2.2.9.dist-info/top_level.txt
pynndb2-2.2.9.dist-info/RECORD
