Metadata-Version: 2.1
Name: pynndb2
Version: 2.2.9
Summary: Database library for Python based on LMDB storage engine
Home-page: https://gitlab.com/oddjobz/pynndb2
Author: Gareth Bult
Author-email: oddjobz@linux.co.uk
License: MIT
Keywords: pynndb,database,LMDB,python
Platform: UNKNOWN
Classifier: Development Status :: 3 - Alpha
Classifier: Intended Audience :: Developers
Classifier: Topic :: Database :: Database Engines/Servers
Classifier: License :: OSI Approved :: MIT License
Classifier: Programming Language :: Python :: 3.7
Requires-Dist: Pipfile
Requires-Dist: importlib-metadata (==1.7.0)
Requires-Dist: lmdb
Requires-Dist: posix-ipc
Requires-Dist: pytest
